pickleplot/__init__.py
pickleplot/__main__.py
pickleplot-0.1.0.dist-info/METADATA
pickleplot-0.1.0.dist-info/WHEEL
pickleplot-0.1.0.dist-info/entry_points.txt
pickleplot-0.1.0.dist-info/RECORD
